pyasassn/__init__.py
pyasassn/client.py
pyasassn/utils.py
pyasassn-0.6.4.dist-info/LICENSE
pyasassn-0.6.4.dist-info/METADATA
pyasassn-0.6.4.dist-info/WHEEL
pyasassn-0.6.4.dist-info/top_level.txt
pyasassn-0.6.4.dist-info/RECORD
