Metadata-Version: 2.1
Name: pyasassn
Version: 0.6.4
Summary: UNKNOWN
Home-page: https://github.com/asas_sn/skypatrol/
Author: Kyle Hart
Author-email: kylehart@hawaii.edu
License: GPL v.3
Platform: UNKNOWN
License-File: LICENSE
Requires-Dist: requests
Requires-Dist: pandas
Requires-Dist: pyarrow (==4.0.1)
Requires-Dist: astropy
Requires-Dist: numpy
Requires-Dist: matplotlib
